LICENSE
MANIFEST.in
README.md
setup.py
pdfkit/__init__.py
pdfkit/api.py
pdfkit/configuration.py
pdfkit/pdfkit.py
pdfkit/source.py
pdfkit_async.egg-info/PKG-INFO
pdfkit_async.egg-info/SOURCES.txt
pdfkit_async.egg-info/dependency_links.txt
pdfkit_async.egg-info/top_level.txt