Metadata-Version: 2.1
Name: pdfkit-async
Version: 0.7.1
Summary: Wkhtmltopdf python wrapper to convert html to pdf using the webkit rendering engine and qt
Home-page: UNKNOWN
Author: Shivansh Saini
Author-email: shivanshs9@gmail.com
License: MIT
Download-URL: https://github.com/shivanshs9/python-pdfkit-async
Platform: UNKNOWN
Classifier: Programming Language :: Python
Classifier: Programming Language :: Python :: 3.5
Classifier: Programming Language :: Python :: 3.6
Classifier: Programming Language :: Python :: 3.7
Classifier: Programming Language :: Python :: 3.8
Classifier: Topic :: Text Processing
Classifier: Topic :: Text Processing :: General
Classifier: Topic :: Text Processing :: Markup
Classifier: Topic :: Text Processing :: Markup :: HTML
Classifier: Topic :: Text Processing :: Markup :: XML
Classifier: Topic :: Utilities
